[
  {
    "MatchNumber": 9,
    "RoundNumber": 1,
    "DateUtc": "2025-08-09 16:45:00Z",
    "Location": "De Kuip",
    "HomeTeam": "Feyenoord",
    "AwayTeam": "NAC Breda",
    "Group": null,
    "HomeTeamScore": 2,
    "AwayTeamScore": 0
  },
  {
    "MatchNumber": 10,
    "RoundNumber": 2,
    "DateUtc": "2025-08-17 18:00:00Z",
    "Location": "Rat Verlegh Stadion",
    "HomeTeam": "NAC Breda",
    "AwayTeam": "Fortuna Sittard",
    "Group": null,
    "HomeTeamScore": 2,
    "AwayTeamScore": 1
  },
  {
    "MatchNumber": 19,
    "RoundNumber": 3,
    "DateUtc": "2025-08-24 12:30:00Z",
    "Location": "Goffertstadion",
    "HomeTeam": "N.E.C. Nijmegen",
    "AwayTeam": "NAC Breda",
    "Group": null,
    "HomeTeamScore": 3,
    "AwayTeamScore": 0
  },
  {
    "MatchNumber": 31,
    "RoundNumber": 4,
    "DateUtc": "2025-08-31 14:45:00Z",
    "Location": "Rat Verlegh Stadion",
    "HomeTeam": "NAC Breda",
    "AwayTeam": "AZ",
    "Group": null,
    "HomeTeamScore": 0,
    "AwayTeamScore": 1
  },
  {
    "MatchNumber": 37,
    "RoundNumber": 5,
    "DateUtc": "2025-09-13 19:00:00Z",
    "Location": "De Grolsch Veste",
    "HomeTeam": "FC Twente",
    "AwayTeam": "NAC Breda",
    "Group": null,
    "HomeTeamScore": 2,
    "AwayTeamScore": 2
  },
  {
    "MatchNumber": 52,
    "RoundNumber": 6,
    "DateUtc": "2025-09-20 19:00:00Z",
    "Location": "Rat Verlegh Stadion",
    "HomeTeam": "NAC Breda",
    "AwayTeam": "Heracles Almelo",
    "Group": null,
    "HomeTeamScore": null,
    "AwayTeamScore": null
  },
  {
    "MatchNumber": 58,
    "RoundNumber": 7,
    "DateUtc": "2025-09-27 14:30:00Z",
    "Location": "Johan Cruyff Arena",
    "HomeTeam": "Ajax",
    "AwayTeam": "NAC Breda",
    "Group": null,
    "HomeTeamScore": null,
    "AwayTeamScore": null
  },
  {
    "MatchNumber": 72,
    "RoundNumber": 8,
    "DateUtc": "2025-10-03 18:00:00Z",
    "Location": "Rat Verlegh Stadion",
    "HomeTeam": "NAC Breda",
    "AwayTeam": "FC Groningen",
    "Group": null,
    "HomeTeamScore": null,
    "AwayTeamScore": null
  },
  {
    "MatchNumber": 79,
    "RoundNumber": 9,
    "DateUtc": "2025-10-18 19:00:00Z",
    "Location": "Rat Verlegh Stadion",
    "HomeTeam": "NAC Breda",
    "AwayTeam": "PEC Zwolle",
    "Group": null,
    "HomeTeamScore": null,
    "AwayTeamScore": null
  },
  {
    "MatchNumber": 90,
    "RoundNumber": 10,
    "DateUtc": "2025-10-24 18:00:00Z",
    "Location": "Abe Lenstra Stadion",
    "HomeTeam": "sc Heerenveen",
    "AwayTeam": "NAC Breda",
    "Group": null,
    "HomeTeamScore": null,
    "AwayTeamScore": null
  },
  {
    "MatchNumber": 93,
    "RoundNumber": 11,
    "DateUtc": "2025-11-01 17:45:00Z",
    "Location": "Rat Verlegh Stadion",
    "HomeTeam": "NAC Breda",
    "AwayTeam": "Go Ahead Eagles",
    "Group": null,
    "HomeTeamScore": null,
    "AwayTeamScore": null
  },
  {
    "MatchNumber": 108,
    "RoundNumber": 12,
    "DateUtc": "2025-11-08 17:45:00Z",
    "Location": "Kras Stadion",
    "HomeTeam": "FC Volendam",
    "AwayTeam": "NAC Breda",
    "Group": null,
    "HomeTeamScore": null,
    "AwayTeamScore": null
  },
  {
    "MatchNumber": 117,
    "RoundNumber": 13,
    "DateUtc": "2025-11-22 15:30:00Z",
    "Location": "Rat Verlegh Stadion",
    "HomeTeam": "NAC Breda",
    "AwayTeam": "PSV",
    "Group": null,
    "HomeTeamScore": null,
    "AwayTeamScore": null
  },
  {
    "MatchNumber": 124,
    "RoundNumber": 14,
    "DateUtc": "2025-11-29 15:30:00Z",
    "Location": "Van Donge & De Roo Stadion",
    "HomeTeam": "Excelsior Rotterdam",
    "AwayTeam": "NAC Breda",
    "Group": null,
    "HomeTeamScore": null,
    "AwayTeamScore": null
  },
  {
    "MatchNumber": 130,
    "RoundNumber": 15,
    "DateUtc": "2025-12-07 15:45:00Z",
    "Location": "Sparta Stadion Het Kasteel",
    "HomeTeam": "Sparta Rotterdam",
    "AwayTeam": "NAC Breda",
    "Group": null,
    "HomeTeamScore": null,
    "AwayTeamScore": null
  },
  {
    "MatchNumber": 143,
    "RoundNumber": 16,
    "DateUtc": "2025-12-14 15:45:00Z",
    "Location": "Rat Verlegh Stadion",
    "HomeTeam": "NAC Breda",
    "AwayTeam": "FC Utrecht",
    "Group": null,
    "HomeTeamScore": null,
    "AwayTeamScore": null
  },
  {
    "MatchNumber": 149,
    "RoundNumber": 17,
    "DateUtc": "2025-12-20 20:00:00Z",
    "Location": "Rat Verlegh Stadion",
    "HomeTeam": "NAC Breda",
    "AwayTeam": "Telstar",
    "Group": null,
    "HomeTeamScore": null,
    "AwayTeamScore": null
  },
  {
    "MatchNumber": 161,
    "RoundNumber": 18,
    "DateUtc": "2026-01-10 20:00:00Z",
    "Location": "Euroborg",
    "HomeTeam": "FC Groningen",
    "AwayTeam": "NAC Breda",
    "Group": null,
    "HomeTeamScore": null,
    "AwayTeamScore": null
  },
  {
    "MatchNumber": 171,
    "RoundNumber": 19,
    "DateUtc": "2026-01-17 20:00:00Z",
    "Location": "Rat Verlegh Stadion",
    "HomeTeam": "NAC Breda",
    "AwayTeam": "N.E.C. Nijmegen",
    "Group": null,
    "HomeTeamScore": null,
    "AwayTeamScore": null
  },
  {
    "MatchNumber": 172,
    "RoundNumber": 20,
    "DateUtc": "2026-01-24 19:00:00Z",
    "Location": "Philips Stadion",
    "HomeTeam": "PSV",
    "AwayTeam": "NAC Breda",
    "Group": null,
    "HomeTeamScore": null,
    "AwayTeamScore": null
  },
  {
    "MatchNumber": 186,
    "RoundNumber": 21,
    "DateUtc": "2026-01-30 19:00:00Z",
    "Location": "Rat Verlegh Stadion",
    "HomeTeam": "NAC Breda",
    "AwayTeam": "FC Twente",
    "Group": null,
    "HomeTeamScore": null,
    "AwayTeamScore": null
  },
  {
    "MatchNumber": 198,
    "RoundNumber": 22,
    "DateUtc": "2026-02-07 00:00:00Z",
    "Location": "Rat Verlegh Stadion",
    "HomeTeam": "NAC Breda",
    "AwayTeam": "Excelsior Rotterdam",
    "Group": null,
    "HomeTeamScore": null,
    "AwayTeamScore": null
  },
  {
    "MatchNumber": 202,
    "RoundNumber": 23,
    "DateUtc": "2026-02-14 00:00:00Z",
    "Location": "Asito Stadion",
    "HomeTeam": "Heracles Almelo",
    "AwayTeam": "NAC Breda",
    "Group": null,
    "HomeTeamScore": null,
    "AwayTeamScore": null
  },
  {
    "MatchNumber": 214,
    "RoundNumber": 24,
    "DateUtc": "2026-02-21 00:00:00Z",
    "Location": "Rat Verlegh Stadion",
    "HomeTeam": "NAC Breda",
    "AwayTeam": "FC Volendam",
    "Group": null,
    "HomeTeamScore": null,
    "AwayTeamScore": null
  },
  {
    "MatchNumber": 221,
    "RoundNumber": 25,
    "DateUtc": "2026-02-28 00:00:00Z",
    "Location": "Sportpark Schoonenberg",
    "HomeTeam": "Telstar",
    "AwayTeam": "NAC Breda",
    "Group": null,
    "HomeTeamScore": null,
    "AwayTeamScore": null
  },
  {
    "MatchNumber": 231,
    "RoundNumber": 26,
    "DateUtc": "2026-03-07 00:00:00Z",
    "Location": "Rat Verlegh Stadion",
    "HomeTeam": "NAC Breda",
    "AwayTeam": "Feyenoord",
    "Group": null,
    "HomeTeamScore": null,
    "AwayTeamScore": null
  },
  {
    "MatchNumber": 240,
    "RoundNumber": 27,
    "DateUtc": "2026-03-14 00:00:00Z",
    "Location": "De Adelaarshorst",
    "HomeTeam": "Go Ahead Eagles",
    "AwayTeam": "NAC Breda",
    "Group": null,
    "HomeTeamScore": null,
    "AwayTeamScore": null
  },
  {
    "MatchNumber": 245,
    "RoundNumber": 28,
    "DateUtc": "2026-03-21 00:00:00Z",
    "Location": "MAC³PARK Stadion",
    "HomeTeam": "PEC Zwolle",
    "AwayTeam": "NAC Breda",
    "Group": null,
    "HomeTeamScore": null,
    "AwayTeamScore": null
  },
  {
    "MatchNumber": 260,
    "RoundNumber": 29,
    "DateUtc": "2026-04-04 00:00:00Z",
    "Location": "Rat Verlegh Stadion",
    "HomeTeam": "NAC Breda",
    "AwayTeam": "Sparta Rotterdam",
    "Group": null,
    "HomeTeamScore": null,
    "AwayTeamScore": null
  },
  {
    "MatchNumber": 267,
    "RoundNumber": 30,
    "DateUtc": "2026-04-11 00:00:00Z",
    "Location": "Fortuna Sittard Stadion",
    "HomeTeam": "Fortuna Sittard",
    "AwayTeam": "NAC Breda",
    "Group": null,
    "HomeTeamScore": null,
    "AwayTeamScore": null
  },
  {
    "MatchNumber": 273,
    "RoundNumber": 31,
    "DateUtc": "2026-04-23 00:00:00Z",
    "Location": "Rat Verlegh Stadion",
    "HomeTeam": "NAC Breda",
    "AwayTeam": "Ajax",
    "Group": null,
    "HomeTeamScore": null,
    "AwayTeamScore": null
  },
  {
    "MatchNumber": 284,
    "RoundNumber": 32,
    "DateUtc": "2026-05-02 00:00:00Z",
    "Location": "Stadion Galgenwaard",
    "HomeTeam": "FC Utrecht",
    "AwayTeam": "NAC Breda",
    "Group": null,
    "HomeTeamScore": null,
    "AwayTeamScore": null
  },
  {
    "MatchNumber": 294,
    "RoundNumber": 33,
    "DateUtc": "2026-05-10 14:45:00Z",
    "Location": "Rat Verlegh Stadion",
    "HomeTeam": "NAC Breda",
    "AwayTeam": "sc Heerenveen",
    "Group": null,
    "HomeTeamScore": null,
    "AwayTeamScore": null
  },
  {
    "MatchNumber": 306,
    "RoundNumber": 34,
    "DateUtc": "2026-05-17 12:30:00Z",
    "Location": "AFAS Stadion",
    "HomeTeam": "AZ",
    "AwayTeam": "NAC Breda",
    "Group": null,
    "HomeTeamScore": null,
    "AwayTeamScore": null
  }
]