[
  {
    "MatchNumber": 2,
    "RoundNumber": 1,
    "DateUtc": "2025-02-22 21:45:00Z",
    "Location": "BMO Stadium",
    "HomeTeam": "LAFC",
    "AwayTeam": "Minnesota",
    "Group": null,
    "HomeTeamScore": 1,
    "AwayTeamScore": 0
  },
  {
    "MatchNumber": 26,
    "RoundNumber": 2,
    "DateUtc": "2025-03-02 03:30:00Z",
    "Location": "BMO Stadium",
    "HomeTeam": "LAFC",
    "AwayTeam": "New York City",
    "Group": null,
    "HomeTeamScore": 1,
    "AwayTeamScore": 0
  },
  {
    "MatchNumber": 32,
    "RoundNumber": 3,
    "DateUtc": "2025-03-08 21:45:00Z",
    "Location": "Lumen Field",
    "HomeTeam": "Seattle",
    "AwayTeam": "LAFC",
    "Group": null,
    "HomeTeamScore": 5,
    "AwayTeamScore": 2
  },
  {
    "MatchNumber": 48,
    "RoundNumber": 4,
    "DateUtc": "2025-03-15 19:45:00Z",
    "Location": "BMO Stadium",
    "HomeTeam": "LAFC",
    "AwayTeam": "Austin",
    "Group": null,
    "HomeTeamScore": 0,
    "AwayTeamScore": 1
  },
  {
    "MatchNumber": 68,
    "RoundNumber": 5,
    "DateUtc": "2025-03-23 00:30:00Z",
    "Location": "Children's Mercy Park",
    "HomeTeam": "Kansas City",
    "AwayTeam": "LAFC",
    "Group": null,
    "HomeTeamScore": 0,
    "AwayTeamScore": 2
  },
  {
    "MatchNumber": 86,
    "RoundNumber": 6,
    "DateUtc": "2025-03-30 02:30:00Z",
    "Location": "Snapdragon Stadium",
    "HomeTeam": "San Diego",
    "AwayTeam": "LAFC",
    "Group": null,
    "HomeTeamScore": 3,
    "AwayTeamScore": 2
  },
  {
    "MatchNumber": 98,
    "RoundNumber": 7,
    "DateUtc": "2025-04-06 01:08:00Z",
    "Location": "Shell Energy Stadium",
    "HomeTeam": "Houston",
    "AwayTeam": "LAFC",
    "Group": null,
    "HomeTeamScore": 1,
    "AwayTeamScore": 0
  },
  {
    "MatchNumber": 116,
    "RoundNumber": 8,
    "DateUtc": "2025-04-13 02:30:00Z",
    "Location": "BMO Stadium",
    "HomeTeam": "LAFC",
    "AwayTeam": "San Jose",
    "Group": null,
    "HomeTeamScore": 2,
    "AwayTeamScore": 1
  },
  {
    "MatchNumber": 133,
    "RoundNumber": 9,
    "DateUtc": "2025-04-20 02:15:00Z",
    "Location": "Providence Park",
    "HomeTeam": "Portland",
    "AwayTeam": "LAFC",
    "Group": null,
    "HomeTeamScore": 3,
    "AwayTeamScore": 3
  },
  {
    "MatchNumber": 149,
    "RoundNumber": 10,
    "DateUtc": "2025-04-27 23:00:00Z",
    "Location": "BMO Stadium",
    "HomeTeam": "LAFC",
    "AwayTeam": "St. Louis",
    "Group": null,
    "HomeTeamScore": 2,
    "AwayTeamScore": 2
  },
  {
    "MatchNumber": 160,
    "RoundNumber": 11,
    "DateUtc": "2025-05-04 02:30:00Z",
    "Location": "BMO Stadium",
    "HomeTeam": "LAFC",
    "AwayTeam": "Houston",
    "Group": null,
    "HomeTeamScore": 2,
    "AwayTeamScore": 0
  },
  {
    "MatchNumber": 179,
    "RoundNumber": 12,
    "DateUtc": "2025-05-11 23:00:00Z",
    "Location": "BC Place",
    "HomeTeam": "Vancouver",
    "AwayTeam": "LAFC",
    "Group": null,
    "HomeTeamScore": 2,
    "AwayTeamScore": 2
  },
  {
    "MatchNumber": 190,
    "RoundNumber": 13,
    "DateUtc": "2025-05-15 02:30:00Z",
    "Location": "BMO Stadium",
    "HomeTeam": "LAFC",
    "AwayTeam": "Seattle",
    "Group": null,
    "HomeTeamScore": 4,
    "AwayTeamScore": 0
  },
  {
    "MatchNumber": 207,
    "RoundNumber": 14,
    "DateUtc": "2025-05-19 01:00:00Z",
    "Location": "Dignity Health Sports Park",
    "HomeTeam": "LA",
    "AwayTeam": "LAFC",
    "Group": null,
    "HomeTeamScore": 2,
    "AwayTeamScore": 2
  },
  {
    "MatchNumber": 212,
    "RoundNumber": 15,
    "DateUtc": "2025-05-24 23:30:00Z",
    "Location": "Stade Saputo",
    "HomeTeam": "Montréal",
    "AwayTeam": "LAFC",
    "Group": null,
    "HomeTeamScore": 2,
    "AwayTeamScore": 2
  },
  {
    "MatchNumber": 234,
    "RoundNumber": 18,
    "DateUtc": "2025-06-09 01:00:00Z",
    "Location": "BMO Stadium",
    "HomeTeam": "LAFC",
    "AwayTeam": "Kansas City",
    "Group": null,
    "HomeTeamScore": 3,
    "AwayTeamScore": 1
  },
  {
    "MatchNumber": 293,
    "RoundNumber": 21,
    "DateUtc": "2025-06-30 01:30:00Z",
    "Location": "BMO Stadium",
    "HomeTeam": "LAFC",
    "AwayTeam": "Vancouver",
    "Group": null,
    "HomeTeamScore": 0,
    "AwayTeamScore": 1
  },
  {
    "MatchNumber": 249,
    "RoundNumber": 22,
    "DateUtc": "2025-07-10 02:25:00Z",
    "Location": "BMO Stadium",
    "HomeTeam": "LAFC",
    "AwayTeam": "Colorado",
    "Group": null,
    "HomeTeamScore": 3,
    "AwayTeamScore": 0
  },
  {
    "MatchNumber": 326,
    "RoundNumber": 23,
    "DateUtc": "2025-07-13 02:30:00Z",
    "Location": "BMO Stadium",
    "HomeTeam": "LAFC",
    "AwayTeam": "Dallas",
    "Group": null,
    "HomeTeamScore": 2,
    "AwayTeamScore": 0
  },
  {
    "MatchNumber": 335,
    "RoundNumber": 24,
    "DateUtc": "2025-07-17 00:30:00Z",
    "Location": "Allianz Field",
    "HomeTeam": "Minnesota",
    "AwayTeam": "LAFC",
    "Group": null,
    "HomeTeamScore": 0,
    "AwayTeamScore": 1
  },
  {
    "MatchNumber": 353,
    "RoundNumber": 25,
    "DateUtc": "2025-07-20 02:30:00Z",
    "Location": "BMO Stadium",
    "HomeTeam": "LAFC",
    "AwayTeam": "LA",
    "Group": null,
    "HomeTeamScore": 3,
    "AwayTeamScore": 3
  },
  {
    "MatchNumber": 360,
    "RoundNumber": 26,
    "DateUtc": "2025-07-26 02:30:00Z",
    "Location": "BMO Stadium",
    "HomeTeam": "LAFC",
    "AwayTeam": "Portland",
    "Group": null,
    "HomeTeamScore": 0,
    "AwayTeamScore": 1
  },
  {
    "MatchNumber": 376,
    "RoundNumber": 27,
    "DateUtc": "2025-08-10 00:30:00Z",
    "Location": "SeatGeek Stadium",
    "HomeTeam": "Chicago",
    "AwayTeam": "LAFC",
    "Group": null,
    "HomeTeamScore": 2,
    "AwayTeamScore": 2
  },
  {
    "MatchNumber": 389,
    "RoundNumber": 28,
    "DateUtc": "2025-08-16 23:30:00Z",
    "Location": "Gillette Stadium",
    "HomeTeam": "New England",
    "AwayTeam": "LAFC",
    "Group": null,
    "HomeTeamScore": 0,
    "AwayTeamScore": 2
  },
  {
    "MatchNumber": 406,
    "RoundNumber": 29,
    "DateUtc": "2025-08-24 00:30:00Z",
    "Location": "Toyota Stadium",
    "HomeTeam": "Dallas",
    "AwayTeam": "LAFC",
    "Group": null,
    "HomeTeamScore": 1,
    "AwayTeamScore": 1
  },
  {
    "MatchNumber": 430,
    "RoundNumber": 30,
    "DateUtc": "2025-09-01 02:45:00Z",
    "Location": "BMO Stadium",
    "HomeTeam": "LAFC",
    "AwayTeam": "San Diego",
    "Group": null,
    "HomeTeamScore": 1,
    "AwayTeamScore": 2
  },
  {
    "MatchNumber": 440,
    "RoundNumber": 32,
    "DateUtc": "2025-09-14 00:30:00Z",
    "Location": "Levi's Stadium",
    "HomeTeam": "San Jose",
    "AwayTeam": "LAFC",
    "Group": null,
    "HomeTeamScore": 2,
    "AwayTeamScore": 4
  },
  {
    "MatchNumber": 280,
    "RoundNumber": 33,
    "DateUtc": "2025-09-18 01:30:00Z",
    "Location": "America First Field",
    "HomeTeam": "Salt Lake",
    "AwayTeam": "LAFC",
    "Group": null,
    "HomeTeamScore": null,
    "AwayTeamScore": null
  },
  {
    "MatchNumber": 464,
    "RoundNumber": 34,
    "DateUtc": "2025-09-22 01:00:00Z",
    "Location": "BMO Stadium",
    "HomeTeam": "LAFC",
    "AwayTeam": "Salt Lake",
    "Group": null,
    "HomeTeamScore": null,
    "AwayTeamScore": null
  },
  {
    "MatchNumber": 474,
    "RoundNumber": 36,
    "DateUtc": "2025-09-28 00:30:00Z",
    "Location": "Energizer Park",
    "HomeTeam": "St. Louis",
    "AwayTeam": "LAFC",
    "Group": null,
    "HomeTeamScore": null,
    "AwayTeamScore": null
  },
  {
    "MatchNumber": 495,
    "RoundNumber": 37,
    "DateUtc": "2025-10-06 01:00:00Z",
    "Location": "BMO Stadium",
    "HomeTeam": "LAFC",
    "AwayTeam": "Atlanta",
    "Group": null,
    "HomeTeamScore": null,
    "AwayTeamScore": null
  },
  {
    "MatchNumber": 257,
    "RoundNumber": 37,
    "DateUtc": "2025-10-09 02:30:00Z",
    "Location": "BMO Stadium",
    "HomeTeam": "LAFC",
    "AwayTeam": "Toronto",
    "Group": null,
    "HomeTeamScore": null,
    "AwayTeamScore": null
  },
  {
    "MatchNumber": 305,
    "RoundNumber": 37,
    "DateUtc": "2025-10-12 23:00:00Z",
    "Location": "Q2 Stadium",
    "HomeTeam": "Austin",
    "AwayTeam": "LAFC",
    "Group": null,
    "HomeTeamScore": null,
    "AwayTeamScore": null
  },
  {
    "MatchNumber": 504,
    "RoundNumber": 38,
    "DateUtc": "2025-10-19 01:00:00Z",
    "Location": "Dick's Sporting Goods Park",
    "HomeTeam": "Colorado",
    "AwayTeam": "LAFC",
    "Group": null,
    "HomeTeamScore": null,
    "AwayTeamScore": null
  }
]